git_backupper/__init__.py
git_backupper/__main__.py
git_backupper/api.py
git_backupper/cache.py
git_backupper/defaults.py
git_backupper/exceptions.py
git_backupper/fs.py
git_backupper/logger_wrapper.py
git_backupper/py.typed
git_backupper/repository.py
git_backupper/settings/__init__.py
git_backupper/settings/fields.py
git_backupper/settings/settings.py
git_backupper-0.3.5.dist-info/LICENSE
git_backupper-0.3.5.dist-info/METADATA
git_backupper-0.3.5.dist-info/WHEEL
git_backupper-0.3.5.dist-info/entry_points.txt
git_backupper-0.3.5.dist-info/top_level.txt
git_backupper-0.3.5.dist-info/RECORD
