Metadata-Version: 2.1
Name: git-backupper
Version: 0.3.5
Summary: Simplest way to backup and restore git repositories
Author-email: Vladislav Punko <iam.vlad.punko@gmail.com>
License: MIT
Project-URL: Issue tracker, https://github.com/vladpunko/git-backupper/issues
Project-URL: Source code, https://github.com/vladpunko/git-backupper
Keywords: automation,git
Classifier: Intended Audience :: Developers
Classifier: Intended Audience :: System Administrators
Classifier: Operating System :: OS Independent
Classifier: Topic :: Software Development :: Libraries :: Python Modules
Classifier: Topic :: Software Development :: Libraries
Classifier: Topic :: Software Development
Classifier: Topic :: Utilities
Classifier: Typing :: Typed
Classifier: License :: OSI Approved :: MIT License
Classifier: Programming Language :: Python :: 3
Classifier: Programming Language :: Python :: 3.9
Classifier: Programming Language :: Python :: 3.10
Classifier: Programming Language :: Python :: 3.11
Requires-Python: >=3.9
License-File: LICENSE
Provides-Extra: dev
Requires-Dist: black (>=23.0.0) ; extra == 'dev'
Requires-Dist: isort (>=5.0.0) ; extra == 'dev'
Requires-Dist: pre-commit (>=3.0.0) ; extra == 'dev'
Provides-Extra: test
Requires-Dist: tox (>=4.0.0) ; extra == 'test'
